{
  "Author":"BeamNG",
  "Body Style":"Shooting Brake",
  "Brand":"Hirochi",
  "Country":"Japan",
  "Derby Class":"Compact Car",
  "Name":"SBR4",
  "Type":"Car",
  "Years":{
    "max":2020,
    "min":2013
  },
  "defaultPaintName1":"Scarlet",
  "default_pc":"TT_AWD_S2_DCT",
  "paints":{
    "Anthracite":{
      "baseColor":[
        0.19,
        0.14,
        0.14,
        1.2
      ],
      "clearcoat":1,
      "clearcoatRoughness":0.03,
      "metallic":1,
      "roughness":0.54
    },
    "Aquamarine":{
      "baseColor":[
        0.05,
        0.5,
        0.7,
        1.2
      ],
      "clearcoat":1,
      "clearcoatRoughness":0.03,
      "metallic":0,
      "roughness":1
    },
    "Brilliance":{
      "baseColor":[
        0.84,
        0.84,
        0.84,
        1.2
      ],
      "clearcoat":1,
      "clearcoatRoughness":0.03,
      "metallic":0.5,
      "roughness":0.6
    },
    "Carbon":{
      "baseColor":[
        0.15,
        0.155,
        0.15,
        1.2
      ],
      "clearcoat":1,
      "clearcoatRoughness":0.03,
      "metallic":0,
      "roughness":1
    },
    "Caustic":{
      "baseColor":[
        1,
        0.32,
        0.14,
        1.2
      ],
      "clearcoat":1,
      "clearcoatRoughness":0.03,
      "metallic":0.8,
      "roughness":0.6
    },
    "Citric":{
      "baseColor":[
        0.651,
        1,
        0,
        1.2
      ],
      "clearcoat":1,
      "clearcoatRoughness":0.03,
      "metallic":0,
      "roughness":1
    },
    "Cobalt":{
      "baseColor":[
        0,
        0.15,
        0.65,
        1.2
      ],
      "clearcoat":1,
      "clearcoatRoughness":0.03,
      "metallic":0,
      "roughness":1
    },
    "Cold Steel":{
      "baseColor":[
        0.149,
        0.241,
        0.391,
        1.2
      ],
      "clearcoat":1,
      "clearcoatRoughness":0.03,
      "metallic":0,
      "roughness":1
    },
    "Cyan Steel":{
      "baseColor":[
        0.047,
        0.234,
        0.33,
        1.2
      ],
      "clearcoat":1,
      "clearcoatRoughness":0.03,
      "metallic":0,
      "roughness":1
    },
    "Dusk":{
      "baseColor":[
        0.06,
        0.04,
        0.16,
        1.2
      ],
      "clearcoat":1,
      "clearcoatRoughness":0.03,
      "metallic":0.95,
      "roughness":0.6
    },
    "Earth":{
      "baseColor":[
        0.22,
        0.19,
        0.18,
        1.2
      ],
      "clearcoat":1,
      "clearcoatRoughness":0.03,
      "metallic":0.9,
      "roughness":0.6
    },
    "Electric":{
      "baseColor":[
        0,
        0.31,
        0.89,
        0.75
      ],
      "clearcoat":1,
      "clearcoatRoughness":0.03,
      "metallic":0.8,
      "roughness":0.5
    },
    "Ember":{
      "baseColor":[
        0.7,
        0.4,
        0,
        1.95
      ],
      "clearcoat":1,
      "clearcoatRoughness":0.03,
      "metallic":0,
      "roughness":1
    },
    "Fern":{
      "baseColor":[
        0.12,
        0.28,
        0.18,
        1.2
      ],
      "clearcoat":1,
      "clearcoatRoughness":0.03,
      "metallic":0,
      "roughness":1
    },
    "Ferric":{
      "baseColor":[
        0.42,
        0.18,
        0.11,
        1.4
      ],
      "clearcoat":1,
      "clearcoatRoughness":0.03,
      "metallic":0,
      "roughness":1
    },
    "Forest":{
      "baseColor":[
        0.08,
        0.18,
        0.105,
        1.2
      ],
      "clearcoat":1,
      "clearcoatRoughness":0.03,
      "metallic":0,
      "roughness":1
    },
    "Galvanus":{
      "baseColor":[
        0.63,
        0.61,
        0.59,
        1.2
      ],
      "clearcoat":1,
      "clearcoatRoughness":0.03,
      "metallic":0,
      "roughness":1
    },
    "Ghrome":{
      "baseColor":[
        0.188,
        0.741,
        0.541,
        0.6
      ],
      "clearcoat":1,
      "clearcoatRoughness":0.03,
      "metallic":0.95,
      "roughness":0.18
    },
    "Incendiary":{
      "baseColor":[
        0.95,
        0.08,
        0.02,
        1.2
      ],
      "clearcoat":1,
      "clearcoatRoughness":0.03,
      "metallic":0,
      "roughness":1
    },
    "Lightning":{
      "baseColor":[
        0.5,
        0.77,
        0.95,
        1.2
      ],
      "clearcoat":1,
      "clearcoatRoughness":0.03,
      "metallic":0,
      "roughness":1
    },
    "Lime":{
      "baseColor":[
        0.486,
        0.694,
        0,
        1.2
      ],
      "clearcoat":1,
      "clearcoatRoughness":0.03,
      "metallic":0,
      "roughness":1
    },
    "Liquid Turquoise":{
      "baseColor":[
        0.01,
        0.643,
        0.94,
        0.6
      ],
      "clearcoat":1,
      "clearcoatRoughness":0.03,
      "metallic":0,
      "roughness":1
    },
    "Mammatus":{
      "baseColor":[
        0.21,
        0.23,
        0.22,
        1.5
      ],
      "clearcoat":1,
      "clearcoatRoughness":0.03,
      "metallic":0,
      "roughness":1
    },
    "Marine":{
      "baseColor":[
        0,
        0.124,
        0.355,
        1.2
      ],
      "clearcoat":1,
      "clearcoatRoughness":0.03,
      "metallic":0,
      "roughness":1
    },
    "Mica":{
      "baseColor":[
        0.5,
        0.42,
        0.39,
        1.2
      ],
      "clearcoat":1,
      "clearcoatRoughness":0.03,
      "metallic":0,
      "roughness":1
    },
    "Mist":{
      "baseColor":[
        0.6,
        0.76,
        0.88,
        1.3
      ],
      "clearcoat":1,
      "clearcoatRoughness":0.03,
      "metallic":0,
      "roughness":1
    },
    "Moonset":{
      "baseColor":[
        0.045,
        0.09,
        0.18,
        1.2
      ],
      "clearcoat":1,
      "clearcoatRoughness":0.03,
      "metallic":0,
      "roughness":1
    },
    "Opal":{
      "baseColor":[
        0.22,
        0.37,
        0.33,
        1.2
      ],
      "clearcoat":1,
      "clearcoatRoughness":0.03,
      "metallic":0,
      "roughness":1
    },
    "Pitch":{
      "baseColor":[
        0.002,
        0.012,
        0.008,
        1.2
      ],
      "clearcoat":1,
      "clearcoatRoughness":0.03,
      "metallic":1,
      "roughness":1
    },
    "Plum":{
      "baseColor":[
        0.242,
        0.11,
        0.124,
        1.2
      ],
      "clearcoat":1,
      "clearcoatRoughness":0.03,
      "metallic":0,
      "roughness":1
    },
    "Quicksilver":{
      "baseColor":[
        0.52,
        0.485,
        0.46,
        1.2
      ],
      "clearcoat":1,
      "clearcoatRoughness":0.03,
      "metallic":1,
      "roughness":0.65
    },
    "Rallysport":{
      "baseColor":[
        0,
        0.05,
        0.55,
        1.2
      ],
      "clearcoat":1,
      "clearcoatRoughness":0.03,
      "metallic":0,
      "roughness":1
    },
    "Scarlet":{
      "baseColor":[
        0.68,
        0.1,
        0.11,
        1.2
      ],
      "clearcoat":1,
      "clearcoatRoughness":0.03,
      "metallic":0,
      "roughness":1
    },
    "Shale":{
      "baseColor":[
        0.22,
        0.27,
        0.23,
        1.2
      ],
      "clearcoat":1,
      "clearcoatRoughness":0.03,
      "metallic":0,
      "roughness":1
    },
    "Skyline":{
      "baseColor":[
        0.052,
        0.448,
        0.921,
        1.2
      ],
      "clearcoat":1,
      "clearcoatRoughness":0.03,
      "metallic":0,
      "roughness":1
    },
    "Solar":{
      "baseColor":[
        0.95,
        0.7,
        0.1,
        1.2
      ],
      "clearcoat":1,
      "clearcoatRoughness":0.03,
      "metallic":0,
      "roughness":1
    },
    "Spearmint":{
      "baseColor":[
        0.451,
        0.525,
        0.541,
        1.95
      ],
      "clearcoat":1,
      "clearcoatRoughness":0.03,
      "metallic":0,
      "roughness":1
    },
    "Submarine":{
      "baseColor":[
        0,
        0.06,
        0.16,
        1.2
      ],
      "clearcoat":1,
      "clearcoatRoughness":0.03,
      "metallic":0,
      "roughness":1
    },
    "Superba":{
      "baseColor":[
        0.3,
        0.45,
        0.6,
        1.2
      ],
      "clearcoat":1,
      "clearcoatRoughness":0.03,
      "metallic":0,
      "roughness":1
    },
    "Technetium":{
      "baseColor":[
        0.25,
        0.35,
        0.41,
        1.2
      ],
      "clearcoat":1,
      "clearcoatRoughness":0.03,
      "metallic":1,
      "roughness":0.6
    },
    "Tropic":{
      "baseColor":[
        0.01,
        0.643,
        0.94,
        1.95
      ],
      "clearcoat":1,
      "clearcoatRoughness":0.2,
      "metallic":0,
      "roughness":1
    },
    "Verdant":{
      "baseColor":[
        0.18,
        0.36,
        0.09,
        1.2
      ],
      "clearcoat":1,
      "clearcoatRoughness":0.03,
      "metallic":0,
      "roughness":1
    },
    "Yellowjacket":{
      "baseColor":[
        0.96,
        0.8,
        0,
        1.7
      ],
      "clearcoat":1,
      "clearcoatRoughness":0.03,
      "metallic":0,
      "roughness":1
    }
  }
}